dpdispatcher/__init__.py
dpdispatcher/__main__.py
dpdispatcher/_version.py
dpdispatcher/arginfo.py
dpdispatcher/base_context.py
dpdispatcher/dlog.py
dpdispatcher/dpdisp.py
dpdispatcher/machine.py
dpdispatcher/run.py
dpdispatcher/submission.py
dpdispatcher/contexts/__init__.py
dpdispatcher/contexts/dp_cloud_server_context.py
dpdispatcher/contexts/hdfs_context.py
dpdispatcher/contexts/lazy_local_context.py
dpdispatcher/contexts/local_context.py
dpdispatcher/contexts/openapi_context.py
dpdispatcher/contexts/ssh_context.py
dpdispatcher/dpcloudserver/__init__.py
dpdispatcher/dpcloudserver/client.py
dpdispatcher/entrypoints/__init__.py
dpdispatcher/entrypoints/gui.py
dpdispatcher/entrypoints/run.py
dpdispatcher/entrypoints/submission.py
dpdispatcher/machines/JH_UniScheduler.py
dpdispatcher/machines/__init__.py
dpdispatcher/machines/distributed_shell.py
dpdispatcher/machines/dp_cloud_server.py
dpdispatcher/machines/fugaku.py
dpdispatcher/machines/lsf.py
dpdispatcher/machines/openapi.py
dpdispatcher/machines/pbs.py
dpdispatcher/machines/shell.py
dpdispatcher/machines/slurm.py
dpdispatcher/utils/__init__.py
dpdispatcher/utils/hdfs_cli.py
dpdispatcher/utils/job_status.py
dpdispatcher/utils/record.py
dpdispatcher/utils/utils.py
dpdispatcher/utils/dpcloudserver/__init__.py
dpdispatcher/utils/dpcloudserver/client.py
dpdispatcher/utils/dpcloudserver/config.py
dpdispatcher/utils/dpcloudserver/retcode.py
dpdispatcher/utils/dpcloudserver/zip_file.py
dpdispatcher-1.0.0.dist-info/licenses/LICENSE
dpdispatcher-1.0.0.dist-info/METADATA
dpdispatcher-1.0.0.dist-info/WHEEL
dpdispatcher-1.0.0.dist-info/entry_points.txt
dpdispatcher-1.0.0.dist-info/top_level.txt
dpdispatcher-1.0.0.dist-info/RECORD
