Metadata-Version: 2.4
Name: dpdispatcher
Version: 1.0.0
Summary: Generate HPC scheduler systems jobs input scripts, submit these scripts to HPC systems, and poke until they finish
Author: DeepModeling
License:                    GNU LESSER GENERAL PUBLIC LICENSE
Project-URL: Homepage, https://github.com/deepmodeling/dpdispatcher
Project-URL: documentation, https://docs.deepmodeling.com/projects/dpdispatcher
Project-URL: repository, https://github.com/deepmodeling/dpdispatcher
Keywords: dispatcher,hpc,slurm,lsf,pbs,ssh,jh_unischeduler
Classifier: Programming Language :: Python :: 3.7
Classifier: Programming Language :: Python :: 3.8
Classifier: Programming Language :: Python :: 3.9
Classifier: Programming Language :: Python :: 3.10
Classifier: Programming Language :: Python :: 3.11
Classifier: Operating System :: POSIX :: Linux
Classifier: Operating System :: MacOS :: MacOS X
Classifier: Operating System :: Microsoft :: Windows
Classifier: License :: OSI Approved :: GNU Lesser General Public License v3 (LGPLv3)
Requires-Python: >=3.7
License-File: LICENSE
Requires-Dist: paramiko
Requires-Dist: dargs>=0.4.1
Requires-Dist: requests
Requires-Dist: tqdm>=4.9.0
Requires-Dist: typing_extensions; python_version < "3.7"
Requires-Dist: pyyaml
Requires-Dist: tomli>=1.1.0; python_version < "3.11"
Provides-Extra: docs
Requires-Dist: sphinx; extra == "docs"
Requires-Dist: myst-parser; extra == "docs"
Requires-Dist: sphinx-book-theme; extra == "docs"
Requires-Dist: numpydoc; extra == "docs"
Requires-Dist: deepmodeling-sphinx>=0.3.0; extra == "docs"
Requires-Dist: dargs>=0.3.1; extra == "docs"
Requires-Dist: sphinx-argparse<0.5.0; extra == "docs"
Provides-Extra: cloudserver
Requires-Dist: oss2; extra == "cloudserver"
Requires-Dist: tqdm; extra == "cloudserver"
Requires-Dist: bohrium-sdk; extra == "cloudserver"
Provides-Extra: bohrium
Requires-Dist: oss2; extra == "bohrium"
Requires-Dist: tqdm; extra == "bohrium"
Requires-Dist: bohrium-sdk; extra == "bohrium"
Provides-Extra: gui
Requires-Dist: dpgui; extra == "gui"
Provides-Extra: test
Requires-Dist: dpgui; extra == "test"
Dynamic: license-file
